{
  "generated_at": "2026-04-10 21:49:06",
  "summary": {
    "date": "2026-04-10",
    "cash": 6575.0,
    "market_value": 191950.0,
    "total_assets": 198525.0,
    "total_pnl": -1475.0,
    "total_pnl_pct": -0.74,
    "positions_detail": [
      {
        "stock_id": "2882",
        "name": "國泰金",
        "shares": 1000,
        "avg_cost": 73.8,
        "market_price": 72.9,
        "market_value": 72900.0,
        "unrealized": -900.0,
        "unrealized_pct": -1.22
      },
      {
        "stock_id": "2886",
        "name": "兆豐金",
        "shares": 1000,
        "avg_cost": 39.35,
        "market_price": 39.85,
        "market_value": 39850.0,
        "unrealized": 500.0,
        "unrealized_pct": 1.27
      },
      {
        "stock_id": "2884",
        "name": "玉山金",
        "shares": 1000,
        "avg_cost": 32.6,
        "market_price": 32.25,
        "market_value": 32250.0,
        "unrealized": -350.0,
        "unrealized_pct": -1.07
      },
      {
        "stock_id": "1301",
        "name": "台塑",
        "shares": 1000,
        "avg_cost": 47.4,
        "market_price": 46.95,
        "market_value": 46950.0,
        "unrealized": -450.0,
        "unrealized_pct": -0.95
      }
    ]
  },
  "trades_today": [],
  "all_signals": {
    "2330": {
      "action": "BUY",
      "confidence": 35,
      "price": 2000.0,
      "rsi": 55.0,
      "ma5": 1886.0,
      "ma20": 1853.5247924804687,
      "bb_upper": 1957.4377212162588,
      "bb_lower": 1749.6118637446787,
      "vol_ratio": 0.9708918300037843,
      "reason": [
        "MA5 上穿 MA20（黃金交叉）"
      ]
    },
    "2317": {
      "action": "HOLD",
      "confidence": 0,
      "price": 200.5,
      "rsi": 41.525423728813564,
      "ma5": 196.7,
      "ma20": 202.525,
      "bb_upper": 220.66038268863272,
      "bb_lower": 184.3896173113673,
      "vol_ratio": 0.7295164159473194,
      "reason": [
        "無明確訊號"
      ]
    },
    "2454": {
      "action": "HOLD",
      "confidence": 0,
      "price": 1575.0,
      "rsi": 31.764705882352942,
      "ma5": 1511.0,
      "ma20": 1620.75,
      "bb_upper": 1828.9319801090028,
      "bb_lower": 1412.5680198909972,
      "vol_ratio": 1.1181967228815735,
      "reason": [
        "RSI=31.8 偏低（< 40）"
      ]
    },
    "2382": {
      "action": "SELL",
      "confidence": 50,
      "price": 321.5,
      "rsi": 62.65822784810126,
      "ma5": 296.9,
      "ma20": 288.7,
      "bb_upper": 305.39036911073674,
      "bb_lower": 272.00963088926324,
      "vol_ratio": 2.6923060514374995,
      "reason": [
        "RSI=62.7 偏高（> 60）",
        "股價碰觸布林上軌（超買回落訊號）",
        "成交量放大 2.7x（賣訊確認）"
      ]
    },
    "2308": {
      "action": "SELL",
      "confidence": 35,
      "price": 1735.0,
      "rsi": 61.25,
      "ma5": 1546.0,
      "ma20": 1467.25,
      "bb_upper": 1634.282143140488,
      "bb_lower": 1300.217856859512,
      "vol_ratio": 1.275297755270809,
      "reason": [
        "RSI=61.2 偏高（> 60）",
        "股價碰觸布林上軌（超買回落訊號）"
      ]
    },
    "2881": {
      "action": "HOLD",
      "confidence": 0,
      "price": 87.6,
      "rsi": 45.96774491261273,
      "ma5": 88.2,
      "ma20": 88.2,
      "bb_upper": 90.29761754320195,
      "bb_lower": 86.10238245679805,
      "vol_ratio": 1.1897555319342374,
      "reason": [
        "無明確訊號"
      ]
    },
    "2882": {
      "action": "HOLD",
      "confidence": 0,
      "price": 72.9,
      "rsi": 51.11109415690104,
      "ma5": 72.60000152587891,
      "ma20": 71.8800006866455,
      "bb_upper": 73.95298388832877,
      "bb_lower": 69.80701748496223,
      "vol_ratio": 1.2074445923598474,
      "reason": [
        "無明確訊號"
      ]
    },
    "2886": {
      "action": "HOLD",
      "confidence": 0,
      "price": 39.85,
      "rsi": 55.84415069699789,
      "ma5": 39.34000015258789,
      "ma20": 39.027499771118165,
      "bb_upper": 39.719920992903326,
      "bb_lower": 38.335078549333005,
      "vol_ratio": 1.3357230818043362,
      "reason": [
        "股價碰觸布林上軌（超買回落訊號）"
      ]
    },
    "2884": {
      "action": "BUY",
      "confidence": 35,
      "price": 32.25,
      "rsi": 54.117640194989896,
      "ma5": 32.380000305175784,
      "ma20": 32.22999982833862,
      "bb_upper": 33.26892608449511,
      "bb_lower": 31.191073572182134,
      "vol_ratio": 0.7816491726719043,
      "reason": [
        "MA5 上穿 MA20（黃金交叉）"
      ]
    },
    "2891": {
      "action": "HOLD",
      "confidence": 0,
      "price": 54.0,
      "rsi": 55.8139528006676,
      "ma5": 55.05999984741211,
      "ma20": 52.819999885559085,
      "bb_upper": 55.92896817298103,
      "bb_lower": 49.71103159813714,
      "vol_ratio": 1.5008401026886355,
      "reason": [
        "無明確訊號"
      ]
    },
    "1301": {
      "action": "BUY",
      "confidence": 35,
      "price": 46.95,
      "rsi": 50.31847876609797,
      "ma5": 46.93000106811523,
      "ma20": 46.71500034332276,
      "bb_upper": 48.76698217352468,
      "bb_lower": 44.66301851312083,
      "vol_ratio": 0.6391137113753215,
      "reason": [
        "MA5 上穿 MA20（黃金交叉）"
      ]
    },
    "1303": {
      "action": "BUY",
      "confidence": 35,
      "price": 81.6,
      "rsi": 48.97119322183112,
      "ma5": 81.31999816894532,
      "ma20": 79.99499969482422,
      "bb_upper": 89.99257052308523,
      "bb_lower": 69.9974288665632,
      "vol_ratio": 1.3225041793413166,
      "reason": [
        "MA5 上穿 MA20（黃金交叉）"
      ]
    },
    "6505": {
      "action": "BUY",
      "confidence": 35,
      "price": 52.0,
      "rsi": 35.76159408848329,
      "ma5": 54.84000015258789,
      "ma20": 56.09000034332276,
      "bb_upper": 59.14521226166528,
      "bb_lower": 53.034788424980235,
      "vol_ratio": 0.6313692595574687,
      "reason": [
        "RSI=35.8 偏低（< 40）",
        "股價碰觸布林下軌（超賣反彈訊號）"
      ]
    },
    "2002": {
      "action": "SELL",
      "confidence": 35,
      "price": 20.05,
      "rsi": 60.22727765327045,
      "ma5": 19.730000305175782,
      "ma20": 19.375,
      "bb_upper": 20.05051216192559,
      "bb_lower": 18.69948783807441,
      "vol_ratio": 1.1855935043691295,
      "reason": [
        "RSI=60.2 偏高（> 60）",
        "股價碰觸布林上軌（超買回落訊號）"
      ]
    },
    "1326": {
      "action": "HOLD",
      "confidence": 0,
      "price": 45.45,
      "rsi": 49.02506288939946,
      "ma5": 45.30999908447266,
      "ma20": 44.69999961853027,
      "bb_upper": 47.86394105799962,
      "bb_lower": 41.53605817906092,
      "vol_ratio": 0.7296312598146952,
      "reason": [
        "無明確訊號"
      ]
    },
    "2412": {
      "action": "HOLD",
      "confidence": 0,
      "price": 135.5,
      "rsi": 35.294117647058826,
      "ma5": 134.2,
      "ma20": 134.875,
      "bb_upper": 137.30019668220297,
      "bb_lower": 132.44980331779703,
      "vol_ratio": 1.156933826473879,
      "reason": [
        "RSI=35.3 偏低（< 40）"
      ]
    },
    "3008": {
      "action": "HOLD",
      "confidence": 0,
      "price": 2310.0,
      "rsi": 40.322580645161295,
      "ma5": 2212.0,
      "ma20": 2256.331579589844,
      "bb_upper": 2400.325589061039,
      "bb_lower": 2112.3375701186487,
      "vol_ratio": 1.0045449287536097,
      "reason": [
        "無明確訊號"
      ]
    },
    "2357": {
      "action": "HOLD",
      "confidence": 0,
      "price": 578.0,
      "rsi": 40.298507462686565,
      "ma5": 560.4,
      "ma20": 572.35,
      "bb_upper": 599.9278324402995,
      "bb_lower": 544.7721675597005,
      "vol_ratio": 0.5353309555425889,
      "reason": [
        "無明確訊號"
      ]
    },
    "4938": {
      "action": "HOLD",
      "confidence": 0,
      "price": 80.7,
      "rsi": 55.35715096661687,
      "ma5": 78.73999938964843,
      "ma20": 77.51499938964844,
      "bb_upper": 82.1043577283444,
      "bb_lower": 72.92564105095248,
      "vol_ratio": 0.5195846842081707,
      "reason": [
        "無明確訊號"
      ]
    },
    "3711": {
      "action": "SELL",
      "confidence": 35,
      "price": 393.0,
      "rsi": 60.176991150442475,
      "ma5": 369.8,
      "ma20": 350.375,
      "bb_upper": 382.92758903115987,
      "bb_lower": 317.82241096884013,
      "vol_ratio": 1.1573149336368678,
      "reason": [
        "RSI=60.2 偏高（> 60）",
        "股價碰觸布林上軌（超買回落訊號）"
      ]
    },
    "2603": {
      "action": "HOLD",
      "confidence": 0,
      "price": 202.5,
      "rsi": 30.769230769230774,
      "ma5": 203.0,
      "ma20": 207.5,
      "bb_upper": 220.38001307616253,
      "bb_lower": 194.61998692383747,
      "vol_ratio": 0.548478993495208,
      "reason": [
        "RSI=30.8 偏低（< 40）"
      ]
    },
    "2609": {
      "action": "HOLD",
      "confidence": 0,
      "price": 51.3,
      "rsi": 21.3114682335696,
      "ma5": 51.9,
      "ma20": 54.964999961853025,
      "bb_upper": 62.01229106491237,
      "bb_lower": 47.91770885879368,
      "vol_ratio": 0.6313117218935402,
      "reason": [
        "RSI=21.3 超賣（< 30）"
      ]
    },
    "2615": {
      "action": "HOLD",
      "confidence": 0,
      "price": 77.1,
      "rsi": 46.22641950792575,
      "ma5": 78.86000213623046,
      "ma20": 77.8800006866455,
      "bb_upper": 81.84649295396144,
      "bb_lower": 73.91350841932956,
      "vol_ratio": 0.8706090258168082,
      "reason": [
        "無明確訊號"
      ]
    },
    "2618": {
      "action": "HOLD",
      "confidence": 0,
      "price": 34.85,
      "rsi": 44.5312486030173,
      "ma5": 34.89000015258789,
      "ma20": 34.812500190734866,
      "bb_upper": 36.08234256626377,
      "bb_lower": 33.54265781520596,
      "vol_ratio": 0.5995507180679512,
      "reason": [
        "無明確訊號"
      ]
    },
    "5880": {
      "action": "HOLD",
      "confidence": 0,
      "price": 23.85,
      "rsi": 63.934404700708775,
      "ma5": 23.809999847412108,
      "ma20": 23.307500076293945,
      "bb_upper": 24.056024825529033,
      "bb_lower": 22.558975327058857,
      "vol_ratio": 1.1292977293255415,
      "reason": [
        "RSI=63.9 偏高（> 60）"
      ]
    }
  },
  "portfolio": {
    "cash": 6575.0,
    "positions": {
      "2882": {
        "shares": 1000,
        "avg_cost": 73.8,
        "name": "國泰金"
      },
      "2886": {
        "shares": 1000,
        "avg_cost": 39.35,
        "name": "兆豐金"
      },
      "2884": {
        "shares": 1000,
        "avg_cost": 32.6,
        "name": "玉山金"
      },
      "1301": {
        "shares": 1000,
        "avg_cost": 47.4,
        "name": "台塑"
      }
    },
    "daily_log": [
      {
        "date": "2026-04-09",
        "cash": 86689.0,
        "market_value": 113350.0,
        "total_assets": 200039.0,
        "total_pnl": 39.0,
        "total_pnl_pct": 0.02,
        "positions_detail": [
          {
            "stock_id": "2882",
            "name": "國泰金",
            "shares": 1000,
            "avg_cost": 73.8,
            "market_price": 73.6,
            "market_value": 73600.0,
            "unrealized": -200.0,
            "unrealized_pct": -0.27
          },
          {
            "stock_id": "2886",
            "name": "兆豐金",
            "shares": 1000,
            "avg_cost": 39.35,
            "market_price": 39.75,
            "market_value": 39750.0,
            "unrealized": 400.0,
            "unrealized_pct": 1.02
          }
        ]
      },
      {
        "date": "2026-04-10",
        "cash": 6575.0,
        "market_value": 191950.0,
        "total_assets": 198525.0,
        "total_pnl": -1475.0,
        "total_pnl_pct": -0.74,
        "positions_detail": [
          {
            "stock_id": "2882",
            "name": "國泰金",
            "shares": 1000,
            "avg_cost": 73.8,
            "market_price": 72.9,
            "market_value": 72900.0,
            "unrealized": -900.0,
            "unrealized_pct": -1.22
          },
          {
            "stock_id": "2886",
            "name": "兆豐金",
            "shares": 1000,
            "avg_cost": 39.35,
            "market_price": 39.85,
            "market_value": 39850.0,
            "unrealized": 500.0,
            "unrealized_pct": 1.27
          },
          {
            "stock_id": "2884",
            "name": "玉山金",
            "shares": 1000,
            "avg_cost": 32.6,
            "market_price": 32.25,
            "market_value": 32250.0,
            "unrealized": -350.0,
            "unrealized_pct": -1.07
          },
          {
            "stock_id": "1301",
            "name": "台塑",
            "shares": 1000,
            "avg_cost": 47.4,
            "market_price": 46.95,
            "market_value": 46950.0,
            "unrealized": -450.0,
            "unrealized_pct": -0.95
          }
        ]
      }
    ],
    "trade_log": [
      {
        "datetime": "2026-04-09 14:40:42",
        "action": "BUY",
        "stock_id": "2882",
        "name": "國泰金",
        "price": 73.8,
        "shares": 1000,
        "amount": 73800.0,
        "fee": 105,
        "total": 73905.0,
        "trigger": "技術訊號：MA5 上穿 MA20（黃金交叉）、股價碰觸布林上軌（超買回落訊號）",
        "confidence": 35
      },
      {
        "datetime": "2026-04-09 14:40:42",
        "action": "BUY",
        "stock_id": "2886",
        "name": "兆豐金",
        "price": 39.35,
        "shares": 1000,
        "amount": 39350.0,
        "fee": 56,
        "total": 39406.0,
        "trigger": "技術訊號：MA5 上穿 MA20（黃金交叉）",
        "confidence": 35
      },
      {
        "datetime": "2026-04-10 08:51:52",
        "action": "BUY",
        "stock_id": "2884",
        "name": "玉山金",
        "price": 32.6,
        "shares": 1000,
        "amount": 32600.0,
        "fee": 46,
        "total": 32646.0,
        "trigger": "技術訊號：MA5 上穿 MA20（黃金交叉）",
        "confidence": 35
      },
      {
        "datetime": "2026-04-10 08:51:52",
        "action": "BUY",
        "stock_id": "1301",
        "name": "台塑",
        "price": 47.4,
        "shares": 1000,
        "amount": 47400.0,
        "fee": 68,
        "total": 47468.0,
        "trigger": "技術訊號：MA5 上穿 MA20（黃金交叉）",
        "confidence": 35
      }
    ]
  },
  "ai_review": "no_api_key"
}